rensheng_mcp_weather/__init__.py
rensheng_mcp_weather/command.py
rensheng_mcp_weather-0.1.1.dist-info/METADATA
rensheng_mcp_weather-0.1.1.dist-info/WHEEL
rensheng_mcp_weather-0.1.1.dist-info/entry_points.txt
rensheng_mcp_weather-0.1.1.dist-info/top_level.txt
rensheng_mcp_weather-0.1.1.dist-info/RECORD
