Metadata-Version: 2.4
Name: rensheng_mcp_weather
Version: 0.1.1
Summary: rensheng_mcp_weather
Requires-Python: >=3.13
Requires-Dist: mcp[cli]>=1.13.1
